aoidc/__init__.py
aoidc/__main__.py
aoidc/config.py
aoidc/jwt.py
aoidc/utils.py
aoidc/version.py
aoidc/errors/__init__.py
aoidc/oauth2/context.py
aoidc/oauth2/enums.py
aoidc/oauth2/rfc_7591_dynamic_client/__init__.py
aoidc/oauth2/rfc_7591_dynamic_client/enums.py
aoidc/oauth2/rfc_7636_pkce/__init__.py
aoidc/oauth2/rfc_7636_pkce/enums.py
aoidc/oauth2/rfc_8414_server_metadata/__init__.py
aoidc/oauth2/rfc_8414_server_metadata/enum.py
aoidc/oauth2/rfc_8414_server_metadata/metadata.py
aoidc/oauth2/rfc_8414_server_metadata/subtypes.py
aoidc/oidc/__init__.py
aoidc/oidc/oidc.py
aoidc/oidc/discovery/__init__.py
aoidc/oidc/discovery/metadata.py
aoidc-0.0.1.dist-info/METADATA
aoidc-0.0.1.dist-info/WHEEL
aoidc-0.0.1.dist-info/licenses/LICENSE
aoidc-0.0.1.dist-info/RECORD
