Metadata-Version: 2.4
Name: aoidc
Version: 0.0.1
Summary: Suckless implementation of OIDC with asyncs in mind
Author-email: Rubikoid <rubikoid@rubikoid.ru>
License-Expression: MIT
License-File: LICENSE
Classifier: Development Status :: 2 - Pre-Alpha
Classifier: Framework :: AsyncIO
Classifier: Operating System :: OS Independent
Classifier: Programming Language :: Python :: 3
Classifier: Topic :: Security
Requires-Python: <4,>=3.12
Requires-Dist: httpx<1,>=0.28.1
Requires-Dist: joserfc<2,>=1.6.1
Requires-Dist: msgspec<1,>=0.19.0
Requires-Dist: pydantic-settings<3,>=2.8.1
Requires-Dist: pydantic<3,>=2.10.6
